{
  "version": 1,
  "run": {
    "id": "run-2026-03-09T04-04-10-474Z",
    "feature": "story-decompose",
    "startedAt": "2026-03-09T04:04:10.474Z",
    "status": "running",
    "dryRun": false,
    "pid": 10253
  },
  "progress": {
    "total": 4,
    "passed": 3,
    "failed": 0,
    "paused": 0,
    "blocked": 0,
    "pending": 1
  },
  "cost": {
    "spent": 3.14635325,
    "limit": 8
  },
  "current": {
    "storyId": "SD-004",
    "title": "Pipeline integration and CLI entry point",
    "complexity": "medium",
    "tddStrategy": "test-after",
    "model": "balanced",
    "attempt": 1,
    "phase": "routing"
  },
  "iterations": 4,
  "updatedAt": "2026-03-09T05:28:30.041Z",
  "durationMs": 5059567,
  "lastHeartbeat": "2026-03-09T05:28:30.041Z"
}