{
  "version": 1,
  "run": {
    "id": "run-2026-04-03T03-41-14-221Z",
    "feature": "config-profiles",
    "startedAt": "2026-04-03T03:41:14.221Z",
    "status": "running",
    "dryRun": false,
    "pid": 9749
  },
  "progress": {
    "total": 7,
    "passed": 1,
    "failed": 0,
    "paused": 0,
    "blocked": 0,
    "pending": 6
  },
  "cost": {
    "spent": 0.33644535000000003,
    "limit": 30
  },
  "current": {
    "storyId": "US-001-B",
    "title": "Implement parseDotenv() and resolveEnvVars() in src/config/dotenv.ts",
    "complexity": "medium",
    "tddStrategy": "three-session-tdd-lite",
    "model": "balanced",
    "attempt": 1,
    "phase": "routing"
  },
  "iterations": 3,
  "updatedAt": "2026-04-03T03:54:15.219Z",
  "durationMs": 780998,
  "lastHeartbeat": "2026-04-03T03:54:15.219Z"
}